mison/__init__.py
mison/__main__.py
mison/miner/__init__.py
mison/miner/miner.py
mison/networks/__init__.py
mison/networks/network.py
mison/networks/collaboration/__init__.py
mison/networks/collaboration/collaboration.py
mison/networks/coupling/__init__.py
mison/networks/coupling/coupling.py
mison-1.4.0.dist-info/licenses/LICENSE
mison-1.4.0.dist-info/METADATA
mison-1.4.0.dist-info/WHEEL
mison-1.4.0.dist-info/entry_points.txt
mison-1.4.0.dist-info/top_level.txt
mison-1.4.0.dist-info/RECORD
